adalab_cli/__init__.py
adalab_cli/cli/__init__.py
adalab_cli/cli/app.py
adalab_cli/cli/authentication_flows.py
adalab_cli/cli/completion_tree.py
adalab_cli/cli/databases_commands.py
adalab_cli/cli/factory.py
adalab_cli/cli/gallery_commands.py
adalab_cli/cli/interactive.py
adalab_cli/cli/kernel_commands.py
adalab_cli/cli/logger.py
adalab_cli/cli/login_commands.py
adalab_cli/cli/logs_commands.py
adalab_cli/cli/oci_commands.py
adalab_cli/cli/pictures_commands.py
adalab_cli/cli/schedule_commands.py
adalab_cli/cli/user_commands.py
adalab_cli/cli/utils.py
adalab_cli-3.3.0.dist-info/METADATA
adalab_cli-3.3.0.dist-info/WHEEL
adalab_cli-3.3.0.dist-info/entry_points.txt
adalab_cli-3.3.0.dist-info/RECORD
