Metadata-Version: 2.1
Name: adalab-cli
Version: 3.3.0
Summary: The CLI app to interact with AdaLab.
Home-page: https://adamatics.com
Author: Adamatics ApS
Author-email: info@adamatics.com
Requires-Python: >=3.10.0,<4.0.0
Classifier: Development Status :: 4 - Beta
Classifier: Intended Audience :: Developers
Classifier: Operating System :: OS Independent
Classifier: Programming Language :: Python
Classifier: Programming Language :: Python :: 3
Classifier: Programming Language :: Python :: 3.10
Classifier: Programming Language :: Python :: 3.11
Classifier: Programming Language :: Python :: 3.12
Classifier: Topic :: Software Development :: Libraries :: Python Modules
Classifier: Typing :: Typed
Requires-Dist: adalib (>=7.2.0)
Requires-Dist: adalib-auth (>=1.2.2)
Requires-Dist: ascii-magic (>=2.3.0)
Requires-Dist: loguru (>=0.7.2)
Requires-Dist: prompt-toolkit (>=3.0.47)
Requires-Dist: sh (>=2.0.6)
Requires-Dist: tabulate (>=0.9.0)
Requires-Dist: typer (>=0.9.0)
Project-URL: Repository, https://gitlab.com/adamatics/python/adalab-cli
